{"cameraMode":{"drawMode":0,"name":"Shaded","section":"Shading Mode"},"sceneLighting":false,"audioPlay":false,"sceneViewState":{"m_AlwaysRefresh":false,"showFog":true,"showSkybox":false,"showFlares":true,"showImageEffects":true,"showParticleSystems":true,"showVisualEffectGraphs":true,"m_FxEnabled":true},"in2DMode":false,"pivot":{"x":-49.02529525756836,"y":35.89100646972656,"z":-7.000107765197754},"rotation":{"x":0.33965155482292178,"y":-0.6371780633926392,"z":0.37036505341529848,"w":0.5844078660011292},"size":61.10712814331055,"orthographic":false}